<object><points><x>0.043945</x><x>0.93359</x><y>0.0083218</y><y>0.99584</y></points><label>2</label><labelname>facade</labelname><flag>1</flag></object><object><points><x>0.13477</x><x>0.25391</x><y>0.13176</y><y>0.23717</y></points><label>3</label><labelname>window</labelname><flag>1</flag></object><object><points><x>0.13574</x><x>0.25488</x><y>0.40083</y><y>0.50624</y></points><label>3</label><labelname>window</labelname><flag>1</flag></object><object><points><x>0.13672</x><x>0.25586</x><y>0.67268</y><y>0.7767</y></points><label>3</label><labelname>window</labelname><flag>1</flag></object><object><points><x>0.40527</x><x>0.55664</x><y>0.13176</y><y>0.22885</y></points><label>3</label><labelname>window</labelname><flag>1</flag></object><object><points><x>0.4082</x><x>0.55859</x><y>0.40499</y><y>0.50208</y></points><label>3</label><labelname>window</labelname><flag>1</flag></object><object><points><x>0.40527</x><x>0.55566</x><y>0.68655</y><y>0.78363</y></points><label>3</label><labelname>window</labelname><flag>1</flag></object><object><points><x>0.72559</x><x>0.85156</x><y>0.40638</y><y>0.51318</y></points><label>3</label><labelname>window</labelname><flag>1</flag></object><object><points><x>0.71973</x><x>0.8457</x><y>0.12483</y><y>0.23301</y></points><label>3</label><labelname>window</labelname><flag>1</flag></object><object><points><x>0.72168</x><x>0.92871</x><y>0.67684</y><y>0.80028</y></points><label>4</label><labelname>door</labelname><flag>1</flag></object><object><points><x>0.33496</x><x>0.40137</x><y>0.0957</y><y>0.2663</y></points><label>5</label><labelname>cornice</labelname><flag>1</flag></object><object><points><x>0.33301</x><x>0.39844</x><y>0.37032</y><y>0.5423</y></points><label>5</label><labelname>cornice</labelname><flag>1</flag></object><object><points><x>0.33691</x><x>0.40332</x><y>0.64771</y><y>0.81969</y></points><label>5</label><labelname>cornice</labelname><flag>1</flag></object><object><points><x>0.25098</x><x>0.28125</x><y>0.10818</y><y>0.2552</y></points><label>6</label><labelname>sill</labelname><flag>1</flag></object><object><points><x>0.25293</x><x>0.28125</x><y>0.37725</y><y>0.52705</y></points><label>6</label><labelname>sill</labelname><flag>1</flag></object><object><points><x>0.25391</x><x>0.2832</x><y>0.64771</y><y>0.80028</y></points><label>6</label><labelname>sill</labelname><flag>1</flag></object><object><points><x>0.84961</x><x>0.87695</x><y>0.37725</y><y>0.53259</y></points><label>6</label><labelname>sill</labelname><flag>1</flag></object><object><points><x>0.84375</x><x>0.87402</x><y>0.098474</y><y>0.2552</y></points><label>6</label><labelname>sill</labelname><flag>1</flag></object><object><points><x>0.56543</x><x>0.62305</x><y>0.70735</y><y>0.77809</y></points><label>9</label><labelname>deco</labelname><flag>1</flag></object><object><points><x>0.58594</x><x>0.61328</x><y>0.82663</y><y>0.88627</y></points><label>9</label><labelname>deco</labelname><flag>1</flag></object><object><points><x>0.58496</x><x>0.6123</x><y>0.59362</y><y>0.65049</y></points><label>9</label><labelname>deco</labelname><flag>1</flag></object><object><points><x>0.55176</x><x>0.64941</x><y>0.018031</y><y>0.98058</y></points><label>10</label><labelname>molding</labelname><flag>1</flag></object><object><points><x>0.048828</x><x>0.10059</x><y>0.016644</y><y>0.99029</y></points><label>10</label><labelname>molding</labelname><flag>1</flag></object><object><points><x>0.68164</x><x>0.89941</x><y>0.59778</y><y>0.64632</y></points><label>11</label><labelname>pillar</labelname><flag>1</flag></object><object><points><x>0.67969</x><x>0.89844</x><y>0.85021</y><y>0.89043</y></points><label>11</label><labelname>pillar</labelname><flag>1</flag></object><object><points><x>0.89941</x><x>0.92871</x><y>0.59223</y><y>0.65187</y></points><label>11</label><labelname>pillar</labelname><flag>1</flag></object><object><points><x>0.89844</x><x>0.93262</x><y>0.84466</y><y>0.89875</y></points><label>11</label><labelname>pillar</labelname><flag>1</flag></object><object><points><x>0.64844</x><x>0.68164</x><y>0.59778</y><y>0.64632</y></points><label>11</label><labelname>pillar</labelname><flag>1</flag></object><object><points><x>0.64941</x><x>0.67969</x><y>0.85021</y><y>0.89043</y></points><label>11</label><labelname>pillar</labelname><flag>1</flag></object><object><points><x>0.55273</x><x>0.68066</x><y>0.91401</y><y>0.99029</y></points><label>9</label><labelname>deco</labelname><flag>1</flag></object><object><points><x>0.5498</x><x>0.68652</x><y>0.53814</y><y>0.60333</y></points><label>9</label><labelname>deco</labelname><flag>1</flag></object>