<object><points><x>0.22193</x><x>0.95822</x><y>0.092879</y><y>0.93189</y></points><label>2</label><labelname>facade</labelname><flag>1</flag></object><object><points><x>0.54308</x><x>0.61619</x><y>0.84985</y><y>0.9226</y></points><label>3</label><labelname>window</labelname><flag>1</flag></object><object><points><x>0.54308</x><x>0.61358</x><y>0.74768</y><y>0.81269</y></points><label>3</label><labelname>window</labelname><flag>1</flag></object><object><points><x>0.40209</x><x>0.4752</x><y>0.8483</y><y>0.92415</y></points><label>3</label><labelname>window</labelname><flag>1</flag></object><object><points><x>0.68146</x><x>0.75457</x><y>0.84985</y><y>0.92415</y></points><label>3</label><labelname>window</labelname><flag>1</flag></object><object><points><x>0.26371</x><x>0.33943</x><y>0.8483</y><y>0.91796</y></points><label>3</label><labelname>window</labelname><flag>1</flag></object><object><points><x>0.4047</x><x>0.4752</x><y>0.74768</y><y>0.81115</y></points><label>3</label><labelname>window</labelname><flag>1</flag></object><object><points><x>0.26371</x><x>0.3342</x><y>0.74458</y><y>0.8096</y></points><label>3</label><labelname>window</labelname><flag>1</flag></object><object><points><x>0.68146</x><x>0.75196</x><y>0.75077</y><y>0.81424</y></points><label>3</label><labelname>window</labelname><flag>1</flag></object><object><points><x>0.68146</x><x>0.75718</x><y>0.63003</y><y>0.69659</y></points><label>3</label><labelname>window</labelname><flag>1</flag></object><object><points><x>0.54308</x><x>0.60836</x><y>0.63003</y><y>0.69505</y></points><label>3</label><labelname>window</labelname><flag>1</flag></object><object><points><x>0.4047</x><x>0.46997</x><y>0.63003</y><y>0.69505</y></points><label>3</label><labelname>window</labelname><flag>1</flag></object><object><points><x>0.2611</x><x>0.3342</x><y>0.63003</y><y>0.69505</y></points><label>3</label><labelname>window</labelname><flag>1</flag></object><object><points><x>0.2611</x><x>0.3342</x><y>0.51548</y><y>0.58978</y></points><label>3</label><labelname>window</labelname><flag>1</flag></object><object><points><x>0.40209</x><x>0.4752</x><y>0.51548</y><y>0.58978</y></points><label>3</label><labelname>window</labelname><flag>1</flag></object><object><points><x>0.54047</x><x>0.61358</x><y>0.51548</y><y>0.58978</y></points><label>3</label><labelname>window</labelname><flag>1</flag></object><object><points><x>0.67885</x><x>0.75196</x><y>0.51548</y><y>0.58978</y></points><label>3</label><labelname>window</labelname><flag>1</flag></object><object><points><x>0.67885</x><x>0.75196</x><y>0.4257</y><y>0.5</y></points><label>3</label><labelname>window</labelname><flag>1</flag></object><object><points><x>0.54047</x><x>0.61358</x><y>0.43034</y><y>0.50155</y></points><label>3</label><labelname>window</labelname><flag>1</flag></object><object><points><x>0.40209</x><x>0.47258</x><y>0.42879</y><y>0.5</y></points><label>3</label><labelname>window</labelname><flag>1</flag></object><object><points><x>0.2611</x><x>0.3342</x><y>0.42879</y><y>0.5</y></points><label>3</label><labelname>window</labelname><flag>1</flag></object><object><points><x>0.26371</x><x>0.3342</x><y>0.32817</y><y>0.38854</y></points><label>3</label><labelname>window</labelname><flag>1</flag></object><object><points><x>0.40209</x><x>0.47258</x><y>0.32817</y><y>0.38854</y></points><label>3</label><labelname>window</labelname><flag>1</flag></object><object><points><x>0.54047</x><x>0.61097</x><y>0.32663</y><y>0.38545</y></points><label>3</label><labelname>window</labelname><flag>1</flag></object><object><points><x>0.68146</x><x>0.75457</x><y>0.32972</y><y>0.39009</y></points><label>3</label><labelname>window</labelname><flag>1</flag></object><object><points><x>0.54047</x><x>0.61619</x><y>0.21517</y><y>0.27245</y></points><label>3</label><labelname>window</labelname><flag>1</flag></object><object><points><x>0.67885</x><x>0.74674</x><y>0.21672</y><y>0.27399</y></points><label>3</label><labelname>window</labelname><flag>1</flag></object><object><points><x>0.40209</x><x>0.47781</x><y>0.21517</y><y>0.27399</y></points><label>3</label><labelname>window</labelname><flag>1</flag></object><object><points><x>0.26371</x><x>0.33681</x><y>0.21517</y><y>0.27399</y></points><label>3</label><labelname>window</labelname><flag>1</flag></object><object><points><x>0.26632</x><x>0.33943</x><y>0.10836</y><y>0.17337</y></points><label>3</label><labelname>window</labelname><flag>1</flag></object><object><points><x>0.40209</x><x>0.4752</x><y>0.10836</y><y>0.17492</y></points><label>3</label><labelname>window</labelname><flag>1</flag></object><object><points><x>0.53525</x><x>0.60836</x><y>0.10836</y><y>0.17492</y></points><label>3</label><labelname>window</labelname><flag>1</flag></object><object><points><x>0.67624</x><x>0.74674</x><y>0.10991</y><y>0.17647</y></points><label>3</label><labelname>window</labelname><flag>1</flag></object><object><points><x>0.67885</x><x>0.75196</x><y>0.81734</y><y>0.84365</y></points><label>3</label><labelname>window</labelname><flag>1</flag></object><object><points><x>0.54047</x><x>0.61358</x><y>0.81734</y><y>0.8452</y></points><label>3</label><labelname>window</labelname><flag>1</flag></object><object><points><x>0.40209</x><x>0.4752</x><y>0.81734</y><y>0.84365</y></points><label>3</label><labelname>window</labelname><flag>1</flag></object><object><points><x>0.26371</x><x>0.33681</x><y>0.81424</y><y>0.84211</y></points><label>3</label><labelname>window</labelname><flag>1</flag></object><object><points><x>0.2611</x><x>0.3342</x><y>0.59598</y><y>0.62229</y></points><label>3</label><labelname>window</labelname><flag>1</flag></object><object><points><x>0.40209</x><x>0.4752</x><y>0.59598</y><y>0.62229</y></points><label>3</label><labelname>window</labelname><flag>1</flag></object><object><points><x>0.54047</x><x>0.61358</x><y>0.59752</y><y>0.62384</y></points><label>3</label><labelname>window</labelname><flag>1</flag></object><object><points><x>0.26371</x><x>0.33681</x><y>0.39628</y><y>0.4226</y></points><label>3</label><labelname>window</labelname><flag>1</flag></object><object><points><x>0.39948</x><x>0.47258</x><y>0.39474</y><y>0.42105</y></points><label>3</label><labelname>window</labelname><flag>1</flag></object><object><points><x>0.54047</x><x>0.61358</x><y>0.39474</y><y>0.42105</y></points><label>3</label><labelname>window</labelname><flag>1</flag></object><object><points><x>0.68146</x><x>0.75457</x><y>0.39474</y><y>0.42105</y></points><label>3</label><labelname>window</labelname><flag>1</flag></object><object><points><x>0.67363</x><x>0.74674</x><y>0.18111</y><y>0.20743</y></points><label>3</label><labelname>window</labelname><flag>1</flag></object><object><points><x>0.53786</x><x>0.61097</x><y>0.17957</y><y>0.20588</y></points><label>3</label><labelname>window</labelname><flag>1</flag></object><object><points><x>0.26371</x><x>0.33681</x><y>0.17957</y><y>0.20743</y></points><label>3</label><labelname>window</labelname><flag>1</flag></object><object><points><x>0.39948</x><x>0.47258</x><y>0.18266</y><y>0.20898</y></points><label>3</label><labelname>window</labelname><flag>1</flag></object><object><points><x>0.81723</x><x>0.94778</x><y>0.17957</y><y>0.28019</y></points><label>4</label><labelname>door</labelname><flag>1</flag></object><object><points><x>0.26893</x><x>0.3342</x><y>0.10991</y><y>0.17183</y></points><label>8</label><labelname>blind</labelname><flag>1</flag></object><object><points><x>0.4047</x><x>0.47258</x><y>0.10991</y><y>0.17337</y></points><label>8</label><labelname>blind</labelname><flag>1</flag></object><object><points><x>0.54047</x><x>0.60574</x><y>0.10991</y><y>0.17183</y></points><label>8</label><labelname>blind</labelname><flag>1</flag></object><object><points><x>0.67885</x><x>0.74413</x><y>0.11146</y><y>0.17492</y></points><label>8</label><labelname>blind</labelname><flag>1</flag></object><object><points><x>0.68146</x><x>0.74413</x><y>0.21827</y><y>0.27245</y></points><label>8</label><labelname>blind</labelname><flag>1</flag></object><object><points><x>0.54569</x><x>0.60836</x><y>0.21672</y><y>0.2709</y></points><label>8</label><labelname>blind</labelname><flag>1</flag></object><object><points><x>0.40731</x><x>0.46997</x><y>0.21672</y><y>0.27245</y></points><label>8</label><labelname>blind</labelname><flag>1</flag></object><object><points><x>0.26893</x><x>0.3342</x><y>0.21672</y><y>0.27245</y></points><label>8</label><labelname>blind</labelname><flag>1</flag></object><object><points><x>0.4047</x><x>0.46475</x><y>0.32972</y><y>0.3839</y></points><label>8</label><labelname>blind</labelname><flag>1</flag></object><object><points><x>0.4047</x><x>0.4517</x><y>0.39783</y><y>0.4195</y></points><label>8</label><labelname>blind</labelname><flag>1</flag></object><object><points><x>0.54308</x><x>0.61097</x><y>0.39628</y><y>0.4195</y></points><label>8</label><labelname>blind</labelname><flag>1</flag></object><object><points><x>0.68146</x><x>0.74935</x><y>0.39628</y><y>0.4195</y></points><label>8</label><labelname>blind</labelname><flag>1</flag></object><object><points><x>0.68407</x><x>0.74935</x><y>0.33127</y><y>0.387</y></points><label>8</label><labelname>blind</labelname><flag>1</flag></object><object><points><x>0.54308</x><x>0.60836</x><y>0.32817</y><y>0.3839</y></points><label>8</label><labelname>blind</labelname><flag>1</flag></object><object><points><x>0.54308</x><x>0.61097</x><y>0.43189</y><y>0.49845</y></points><label>8</label><labelname>blind</labelname><flag>1</flag></object><object><points><x>0.68407</x><x>0.74935</x><y>0.42879</y><y>0.49845</y></points><label>8</label><labelname>blind</labelname><flag>1</flag></object><object><points><x>0.4047</x><x>0.46997</x><y>0.43034</y><y>0.49845</y></points><label>8</label><labelname>blind</labelname><flag>1</flag></object><object><points><x>0.4047</x><x>0.46997</x><y>0.51858</y><y>0.58824</y></points><label>8</label><labelname>blind</labelname><flag>1</flag></object><object><points><x>0.54308</x><x>0.61097</x><y>0.51703</y><y>0.58669</y></points><label>8</label><labelname>blind</labelname><flag>1</flag></object><object><points><x>0.68407</x><x>0.75196</x><y>0.52012</y><y>0.58824</y></points><label>8</label><labelname>blind</labelname><flag>1</flag></object><object><points><x>0.68146</x><x>0.75457</x><y>0.59598</y><y>0.62384</y></points><label>3</label><labelname>window</labelname><flag>1</flag></object><object><points><x>0.68146</x><x>0.74674</x><y>0.59907</y><y>0.6192</y></points><label>8</label><labelname>blind</labelname><flag>1</flag></object><object><points><x>0.68407</x><x>0.75457</x><y>0.63313</y><y>0.6935</y></points><label>8</label><labelname>blind</labelname><flag>1</flag></object><object><points><x>0.54569</x><x>0.60836</x><y>0.63158</y><y>0.6935</y></points><label>8</label><labelname>blind</labelname><flag>1</flag></object><object><points><x>0.54308</x><x>0.61097</x><y>0.59907</y><y>0.62074</y></points><label>8</label><labelname>blind</labelname><flag>1</flag></object><object><points><x>0.4047</x><x>0.47258</x><y>0.59752</y><y>0.62074</y></points><label>8</label><labelname>blind</labelname><flag>1</flag></object><object><points><x>0.40731</x><x>0.46736</x><y>0.63158</y><y>0.69195</y></points><label>8</label><labelname>blind</labelname><flag>1</flag></object><object><points><x>0.26632</x><x>0.33159</x><y>0.81579</y><y>0.83901</y></points><label>8</label><labelname>blind</labelname><flag>1</flag></object><object><points><x>0.26632</x><x>0.33159</x><y>0.74768</y><y>0.8065</y></points><label>8</label><labelname>blind</labelname><flag>1</flag></object><object><points><x>0.26632</x><x>0.33681</x><y>0.84985</y><y>0.91641</y></points><label>8</label><labelname>blind</labelname><flag>1</flag></object><object><points><x>0.4047</x><x>0.47258</x><y>0.85139</y><y>0.91796</y></points><label>8</label><labelname>blind</labelname><flag>1</flag></object><object><points><x>0.4047</x><x>0.47258</x><y>0.81889</y><y>0.84211</y></points><label>8</label><labelname>blind</labelname><flag>1</flag></object><object><points><x>0.40731</x><x>0.47258</x><y>0.74923</y><y>0.80805</y></points><label>8</label><labelname>blind</labelname><flag>1</flag></object><object><points><x>0.54569</x><x>0.61097</x><y>0.75077</y><y>0.8096</y></points><label>8</label><labelname>blind</labelname><flag>1</flag></object><object><points><x>0.54308</x><x>0.60836</x><y>0.82043</y><y>0.84211</y></points><label>8</label><labelname>blind</labelname><flag>1</flag></object><object><points><x>0.54569</x><x>0.61358</x><y>0.85139</y><y>0.92105</y></points><label>8</label><labelname>blind</labelname><flag>1</flag></object><object><points><x>0.68407</x><x>0.74935</x><y>0.85294</y><y>0.92105</y></points><label>8</label><labelname>blind</labelname><flag>1</flag></object><object><points><x>0.68146</x><x>0.74935</x><y>0.82043</y><y>0.84211</y></points><label>8</label><labelname>blind</labelname><flag>1</flag></object><object><points><x>0.68407</x><x>0.74935</x><y>0.75232</y><y>0.81269</y></points><label>8</label><labelname>blind</labelname><flag>1</flag></object><object><points><x>0.26371</x><x>0.29243</x><y>0.63313</y><y>0.69195</y></points><label>8</label><labelname>blind</labelname><flag>1</flag></object><object><points><x>0.26371</x><x>0.33159</x><y>0.59752</y><y>0.62074</y></points><label>8</label><labelname>blind</labelname><flag>1</flag></object><object><points><x>0.26371</x><x>0.28721</x><y>0.52012</y><y>0.58824</y></points><label>8</label><labelname>blind</labelname><flag>1</flag></object><object><points><x>0.26893</x><x>0.3342</x><y>0.18266</y><y>0.20433</y></points><label>8</label><labelname>blind</labelname><flag>1</flag></object><object><points><x>0.40731</x><x>0.47258</x><y>0.18421</y><y>0.20588</y></points><label>8</label><labelname>blind</labelname><flag>1</flag></object><object><points><x>0.54047</x><x>0.60836</x><y>0.18266</y><y>0.20433</y></points><label>8</label><labelname>blind</labelname><flag>1</flag></object><object><points><x>0.65796</x><x>0.67885</x><y>0.10062</y><y>0.92724</y></points><label>10</label><labelname>molding</labelname><flag>1</flag></object><object><points><x>0.52219</x><x>0.54308</x><y>0.10062</y><y>0.92724</y></points><label>10</label><labelname>molding</labelname><flag>1</flag></object><object><points><x>0.38642</x><x>0.40731</x><y>0.099071</y><y>0.9257</y></points><label>10</label><labelname>molding</labelname><flag>1</flag></object><object><points><x>0.24543</x><x>0.26632</x><y>0.094427</y><y>0.9226</y></points><label>10</label><labelname>molding</labelname><flag>1</flag></object><object><points><x>0.7624</x><x>0.79896</x><y>0.094427</y><y>0.9226</y></points><label>10</label><labelname>molding</labelname><flag>1</flag></object><object><points><x>0.84856</x><x>0.91645</x><y>0.33591</y><y>0.37771</y></points><label>12</label><labelname>shop</labelname><flag>1</flag></object><object><points><x>0.84856</x><x>0.91906</x><y>0.43808</y><y>0.48142</y></points><label>12</label><labelname>shop</labelname><flag>1</flag></object><object><points><x>0.85117</x><x>0.92167</x><y>0.54334</y><y>0.58669</y></points><label>12</label><labelname>shop</labelname><flag>1</flag></object><object><points><x>0.85379</x><x>0.92428</x><y>0.65015</y><y>0.69195</y></points><label>12</label><labelname>shop</labelname><flag>1</flag></object>